{"gameOverBackgroundImage":1,"gameOverCommands":[{"id":-1,"names":{"1":"Continuar"}},{"id":-1,"k":1,"names":{"1":"Tela inicial"}},{"id":-1,"k":2,"names":{"1":"Sair"}}],"gameOverMusic":{"id":-1,"ie":false,"is":false,"name":"<None>","v":{"k":3,"v":100}},"tb":1,"tc":[{"id":-1,"names":{"1":"Novo jogo"}},{"id":-1,"k":1,"names":{"1":"Carregar jogo"}},{"id":-1,"k":2,"names":{"1":"Configurações"}},{"id":-1,"k":3,"names":{"1":"Sair"}}],"tm":{"id":1,"ie":false,"is":false,"name":"TitleScreen1.mp3","v":{"k":3,"v":100}},"ts":[{"id":0,"name":"Keyboard assigments"},{"id":1,"name":"Language"}]}